dataclasses_sql/__init__.py
dataclasses_sql/_version.py
dataclasses_sql/base.py
dataclasses_sql/delete.py
dataclasses_sql/insert.py
dataclasses_sql/select.py
dataclasses_sql/update.py
dataclasses_sql/utils.py
tests/__init__.py
tests/conftest.py
tests/data.py
tests/test_base.py
tests/test_delete.py
tests/test_insert.py
tests/test_select.py
tests/test_update.py
dataclasses_sql-0.3.0.dist-info/LICENSE
dataclasses_sql-0.3.0.dist-info/METADATA
dataclasses_sql-0.3.0.dist-info/WHEEL
dataclasses_sql-0.3.0.dist-info/top_level.txt
dataclasses_sql-0.3.0.dist-info/RECORD
