Metadata-Version: 2.1
Name: dataclasses-sql
Version: 0.3.0
Summary: Using dataclasses with SQL databases.
Home-page: https://github.com/ppinard/dataclasses-sql
Author: Philippe Pinard
Author-email: philippe.pinard@gmail.com
License: MIT license
Platform: UNKNOWN
Classifier: Development Status :: 2 - Pre-Alpha
Classifier: Intended Audience :: Developers
Classifier: License :: OSI Approved :: MIT License
Classifier: Natural Language :: English
Classifier: Programming Language :: Python :: 3
Classifier: Programming Language :: Python :: 3.7
Requires-Dist: loguru
Requires-Dist: sqlalchemy
Provides-Extra: dev
Provides-Extra: test
Requires-Dist: pytest ; extra == 'test'
Requires-Dist: pytest-cov ; extra == 'test'
